src/__init__.py
src/evaluate.py
src/model.py
src/predict.py
src/prepare.py
src/train.py
single_object_detection-0.1.1.dist-info/METADATA
single_object_detection-0.1.1.dist-info/WHEEL
single_object_detection-0.1.1.dist-info/RECORD
