Metadata-Version: 2.1
Name: single-object-detection
Version: 0.1.1
Summary: Detecting single objects in images based on bounding boxes.
License: MIT
Author: Thomas Jonas
Requires-Python: ==3.10.11
Classifier: License :: OSI Approved :: MIT License
Classifier: Programming Language :: Python :: 3
Requires-Dist: mlflow (>=2.13.1,<3.0.0)
Requires-Dist: torch (>=2.3.0,<3.0.0)
Requires-Dist: torchinfo (>=1.8.0,<2.0.0)
Requires-Dist: torchvision (>=0.18.0,<0.19.0)
